README.md
setup.cfg
setup.py
conffu/__init__.py
conffu/_config.py
conffu/_version.py
conffu.egg-info/PKG-INFO
conffu.egg-info/SOURCES.txt
conffu.egg-info/dependency_links.txt
conffu.egg-info/requires.txt
conffu.egg-info/top_level.txt
test/test_arguments.py
test/test_config.py
test/test_config_files.py
test/test_environment.py