Metadata-Version: 2.1
Name: conffu
Version: 2.2.20
Summary: A simple, but powerful JSON, XML and command line configuration package
Home-page: https://gitlab.com/Jaap.vanderVelde/conffu
Author: BMT, Jaap van der Velde
Author-email: jaap.vandervelde@bmtglobal.com
License: MIT
Download-URL: https://gitlab.com/Jaap.vanderVelde/conffu/repository/archive.zip?ref=2.2.20
Keywords: package,download,json,configuration,CLI,parameters
Platform: UNKNOWN
Classifier: Development Status :: 4 - Beta
Classifier: Intended Audience :: Developers
Classifier: Topic :: Software Development :: Build Tools
Classifier: License :: OSI Approved :: MIT License
Classifier: Programming Language :: Python :: 3.4
Requires-Python: >=3.4
Provides-Extra: xml
Provides-Extra: dev
